{
  "version": "7",
  "dialect": "postgresql",
  "entries": [
    {
      "idx": 0,
      "version": "7",
      "when": 1770796866806,
      "tag": "0000_parallel_ultragirl",
      "breakpoints": true
    },
    {
      "idx": 1,
      "version": "7",
      "when": 1770797657930,
      "tag": "0001_pink_pandemic",
      "breakpoints": true
    },
    {
      "idx": 2,
      "version": "7",
      "when": 1770873027264,
      "tag": "0002_chief_quasimodo",
      "breakpoints": true
    },
    {
      "idx": 3,
      "version": "7",
      "when": 1770876732094,
      "tag": "0003_dapper_proudstar",
      "breakpoints": true
    },
    {
      "idx": 4,
      "version": "7",
      "when": 1773973906491,
      "tag": "0004_shallow_skrulls",
      "breakpoints": true
    },
    {
      "idx": 5,
      "version": "7",
      "when": 1774427200898,
      "tag": "0005_cynical_hellion",
      "breakpoints": true
    },
    {
      "idx": 6,
      "version": "7",
      "when": 1774510138496,
      "tag": "0006_add-album-external-id",
      "breakpoints": true
    }
  ]
}